ecdf_estimator/__init__.py
ecdf_estimator/objective_function.py
ecdf_estimator/output.py
ecdf_estimator/select_bins.py
ecdf_estimator/utils.py
ecdf_estimator-0.1.7.dist-info/METADATA
ecdf_estimator-0.1.7.dist-info/WHEEL
ecdf_estimator-0.1.7.dist-info/top_level.txt
ecdf_estimator-0.1.7.dist-info/RECORD
