Metadata-Version: 2.1
Name: ecdf-estimator
Version: 0.1.7
Summary: Python package for parameter estimation of random data
Home-page: https://github.com/AndreasRupp/ecdf_estimator
Author: Andreas Rupp
Author-email: Andreas Rupp <info@rupp.ink>
License: LGPL-2.1
Project-URL: Homepage, https://github.com/AndreasRupp/ecdf_estimator
Project-URL: Bug Tracker, https://github.com/AndreasRupp/ecdf_estimator/issues
Classifier: Programming Language :: Python :: 3
Classifier: License :: OSI Approved :: GNU Lesser General Public License v2 or later (LGPLv2+)
Classifier: Operating System :: OS Independent
Requires-Python: >=3.11.6
Requires-Dist: numpy >=1.25.0
Requires-Dist: scipy >=1.10.1
Requires-Dist: matplotlib >=3.7.1
